itkwasm_mesh_io/__init__.py
itkwasm_mesh_io/_version.py
itkwasm_mesh_io/byu_read_mesh.py
itkwasm_mesh_io/byu_read_mesh_async.py
itkwasm_mesh_io/byu_write_mesh.py
itkwasm_mesh_io/byu_write_mesh_async.py
itkwasm_mesh_io/free_surfer_ascii_read_mesh.py
itkwasm_mesh_io/free_surfer_ascii_read_mesh_async.py
itkwasm_mesh_io/free_surfer_ascii_write_mesh.py
itkwasm_mesh_io/free_surfer_ascii_write_mesh_async.py
itkwasm_mesh_io/free_surfer_binary_read_mesh.py
itkwasm_mesh_io/free_surfer_binary_read_mesh_async.py
itkwasm_mesh_io/free_surfer_binary_write_mesh.py
itkwasm_mesh_io/free_surfer_binary_write_mesh_async.py
itkwasm_mesh_io/mz3_read_mesh.py
itkwasm_mesh_io/mz3_read_mesh_async.py
itkwasm_mesh_io/mz3_read_point_set.py
itkwasm_mesh_io/mz3_read_point_set_async.py
itkwasm_mesh_io/mz3_write_mesh.py
itkwasm_mesh_io/mz3_write_mesh_async.py
itkwasm_mesh_io/mz3_write_point_set.py
itkwasm_mesh_io/mz3_write_point_set_async.py
itkwasm_mesh_io/obj_read_mesh.py
itkwasm_mesh_io/obj_read_mesh_async.py
itkwasm_mesh_io/obj_read_point_set.py
itkwasm_mesh_io/obj_read_point_set_async.py
itkwasm_mesh_io/obj_write_mesh.py
itkwasm_mesh_io/obj_write_mesh_async.py
itkwasm_mesh_io/obj_write_point_set.py
itkwasm_mesh_io/obj_write_point_set_async.py
itkwasm_mesh_io/off_read_mesh.py
itkwasm_mesh_io/off_read_mesh_async.py
itkwasm_mesh_io/off_read_point_set.py
itkwasm_mesh_io/off_read_point_set_async.py
itkwasm_mesh_io/off_write_mesh.py
itkwasm_mesh_io/off_write_mesh_async.py
itkwasm_mesh_io/off_write_point_set.py
itkwasm_mesh_io/off_write_point_set_async.py
itkwasm_mesh_io/read_mesh.py
itkwasm_mesh_io/read_mesh_async.py
itkwasm_mesh_io/read_point_set.py
itkwasm_mesh_io/read_point_set_async.py
itkwasm_mesh_io/stl_read_mesh.py
itkwasm_mesh_io/stl_read_mesh_async.py
itkwasm_mesh_io/stl_write_mesh.py
itkwasm_mesh_io/stl_write_mesh_async.py
itkwasm_mesh_io/swc_read_mesh.py
itkwasm_mesh_io/swc_read_mesh_async.py
itkwasm_mesh_io/swc_write_mesh.py
itkwasm_mesh_io/swc_write_mesh_async.py
itkwasm_mesh_io-1.7.1.dist-info/METADATA
itkwasm_mesh_io-1.7.1.dist-info/WHEEL
itkwasm_mesh_io-1.7.1.dist-info/RECORD
